spistats/__init__.py
spistats/markov.py
spistats/collision/__init__.py
spistats/desynchronization/__init__.py
spistats/desynchronization/dsync_count.py
spistats/desynchronization/law.py
spistats/desynchronization/law_multi.py
spistats/plot/__init__.py
spistats/plot/cdf.py
spistats-0.1.0.dist-info/METADATA
spistats-0.1.0.dist-info/WHEEL
spistats-0.1.0.dist-info/licenses/LICENSE
spistats-0.1.0.dist-info/RECORD
