Metadata-Version: 2.3
Name: spistats
Version: 0.1.0
Summary: Analyse the performances of sequential private identifiers: a LorWan privacy orentied communication protocol.  Efficient numerical method to compute the mass function and the CDF of streaks of repeating events. Expectation of packet loss computed using Markov chains for improved performance.  This work is based on an extention of https://inria.hal.science/hal-04525080.  Please cite this paper if you use this package in your research project.
Project-URL: Homepage, https://gitlab.inria.fr/jaalmoes/spistats
Project-URL: Bug Tracker, https://gitlab.inria.fr/jaalmoes/spistats/issues
Project-URL: Documentation, https://jaalmoes.com/
Author-email: Jan Aalmoes <jan.aalmoes@protonmail.com>
License-File: LICENSE
Classifier: License :: OSI Approved :: GNU General Public License v3 or later (GPLv3+)
Classifier: Operating System :: OS Independent
Classifier: Programming Language :: Python :: 3
Requires-Python: >=3.7
Requires-Dist: matplotlib
Requires-Dist: numpy
Requires-Dist: scipy
